{
  "name" : "1405.1346.pdf",
  "metadata" : {
    "source" : "META",
    "title" : "Метод автоматического построения онтологии предметной области на основе анализа лингвистических характеристик текстового корпу",
    "authors" : [ "Е.А. Оробинская" ],
    "emails" : [ "Olena.Orobinska@univ-lyon2.fr" ],
    "sections" : [ {
      "heading" : null,
      "text" : "Метод автоматического построения онтологии\nпредметной области на основе анализа лингвистических\nхарактеристик текстового корпуса\nЕ.А. Оробинская\nЛионский университет Лион-2 им. Люмьер, Франция\nOlena.Orobinska@univ-lyon2.fr\nАннотация\nВызов сегодняшнего дня,\nобусловленный бурным ростом текстовых хранилищ в глобальной сети Интернет, заключается в том, чтобы «научить» сами информационные системы (ИС) обнаруживать и правильно интерпретировать полезную информацию, предоставляемую текстом.\nРазработка методов автоматического\nанализа текстовой информации и извлечение из полнотекстовых документов релевантных данных является актуальной задачей инженерии знаний в целом и онтологического инжиниринга в частности. Предпосылкой появления прорывных технологий, которые позволи бы ее решить автор считает поиск решений на основе методов системного анализа, как самого\nобъекта исследования  текста, так и поставленных прикладных задач, которые должны быть решены в результате такой обработки. Иными словами, для семантического анализа текстовой информации требуется онтологический подход, т.е. чтобы обнаружить в тексте требуемую информацию, сама ИС должна обладать достаточным объемом лингвистических знаний.\nВведение\nСо ссылкой на [2],[3] можно утверждать, что в\n2011 г. наиболее быстро растущей категорией т. наз. “sweet tools” или интеллектуальных систем были именно онтологии. Обобщая множество сходных определений, напомним, что в настоящее время под онтологией подразумаевается семантическая структура, в явном виде описывающая основные понятия (концепты) предметной области (ПО), связывающие их отношения, а также аксиомы, описывающие правила вывода новых концептов [4].\nДо сих пор, построение онтологии остается приоритетной задачей экспертов ПО, что делает этот процесс очень дорогостящим и долгосрочным.\nИменно этими факторами объясняется большое количество работ, появившихся в последнее время и предлагающих новые методы анализа текста и, на их основе, технологии автоматизированного построения онтологий [2].\nДо начала 2000–ных годов для решения задач анализа текста в основном применялись и развивались статистические методы. С появлением сетевых лексических ресурсов и совершенствованием синтаксических анализаторов линвистические методы привлекают все большее внимание специалистов благодаря высокому качеству результатов, которые обещают такие методы [5]. Поэтому целью данной работы является описание структуры ИС, позволяющей\nобнаруживать в текстовом корпусе релевантные концепты ПО (радиационная защита) на основе использования лингвистических шаблонов, характерных для данной ПО.\nОсновные принципы построения\nонтологий\nАвтор в основном разделяет подход к построению онтологии на основе текста, предложенный Buitelaar и коллегами в 2005 г. [6], известный как Layer Cake. Весь процесс построения онтологии разбит на несколько независимых этапов, на каждом из которых решается одна определенная задача, результаты которой, в свою очередь, служат\nисходными данными для задачи следующего, как правило, более сложного уровня. Согласно этому подходу можно выделить следующую последовательность действий: извлечение из текста\nтерминов-кандидатов  разбиение терминов на\nгруппы (кластеризация)  присвоение\nобобщающего понятия-концепта каждой группе \nопределение отношений между концептами  формирование правил вывода (расширения концептов). Для начальных этапов многочисленные статистические методы позволяют получать весьма качественные результаты (до 90% точности по сравнению с результатами работы экспертов [7]). Труды XV Всероссийской объединенной конференции «Интернет и современное общество» (IMS-2012), Санкт-Петербург, Россия, 2012.\nОднако для построения таксономии понятий и\nобнаружения неткасономических отношений необходима разработка лингвистических методов. В\nчастности, одним из эффективных подходов для\nобнаружения группы синонимов и общего для них гиперонима является использование\nлингвистических шаблонов, предложенных еще M. Hearst [8]. Дальнейшее совершенствование такого подхода зависит от наличия общей теории описания и анализа конкретного языка. В этой связи автор разделяет идею Золотовой Г. А. о том, что синтаксический строй речи (текста) организуется регулярными комбинациями «элементарных» единиц, из которых строятся все другие более сложные (речевые или текстовые) конструкции [9]. В качестве такой единицы выдвинуто понятие синтаксемы. Синтаксемой по Золотовой Г.А. называется минимальная далее неделимая семантико-синтаксическая единица русского языка,\nвыступающая одновременно и как носитель элементарного смысла, и как конструктивный компонент с функциональностью, необходимой и достаточной для построения более сложных синтаксических конструкций.\nПризнаками синтаксемы служат: 1) категориальное значение слова, от которого она образована, 2) определенная (конкретная) морфологическая форма, 3) функциональность, вытекающая из двух первых признаков, как способность реализовываться в определенных позициях (речи, теста), т.е. как возможная роль в построении коммуникативной единицы. Золотова Г.А. различает три таких функциональных роли:\n1) возможность самостоятельного независимого существования синтаксемы;\n2) использование синтаксемы в качестве компонента предложения;\n3) использование синтаксемы в качестве компонента словосочетания (или сочетания слов), так называемое присловное употребление.\nФункциональные свойства синтаксем служат основой для разграничения трех их возможных типов, называемых соответственно, свободными – А (или обладающими полным функциональным репертуаром), обусловленными – Б (способными\nвыполнять функции 2, 3, крайне изредка 1), связанными – В (выступающими только в роли 3). Очевидно, что функциональные свойства синтаксем имеют транзитивный характер.\nРассматривая текст как динамическую систему, мы имеем возможность описать весь процесс построения онтологии как целенаправленную операционную деятельность в пределах данной системы, организованную для решения задач содержательного наполнения элементов онтологии. Математически онтология определяется следующим образом [6]:\n), ,TσΑ,,σR,c,(C,Ο: ΑRR  , где:\n1. C, R, A,T – являются несвязанными множествами, чьи элементы называются\nидентификаторами концептов, отношений, атрибутов и типов данных соответственно; 2. ≤c – полусвязанная таксономия (semi-upper lattice) концептов с общим элементом\nсамого верхнего уровня rootC;\n3. функция σR:RC+ называемая признаком отношения (relation signature); 4. ≤R on R, иерархия отношений где, r1 ≤R r2 подразумевает =|σR(r1)| =|σR(r2)| и\ni(σR(r1)) ≤c i(σR(r2)) для каждого ≤ i ≤ =|σR(r1)|;\n5. функция σA:AC×T называемая признаком атрибута (attribute signature); 6. множество типов данных (datatypes) T, таких как строки, целые числа и т.д.\nДля обеспечения языковой компетентности,\nдостаточной для построения и самообучения онтологии предметной области на базе текста, ИС сама должна обладать знаниями соответствующего порядка, общими (языковыми) и специальными, (относящимися к данной ПО). Такая ИС должна, по сути, объединять в себе две «встроенные» онтологии: онтологию языка (русского) и базовую (стартовую) онтологию ПО. Многочисленные электронные словари-тезаурусы (MRD – machine readable dictionary), с лексикографической разметкой (какие как WordNet и его русскоязычные аналоги RussNet, RuNet и др.) можно рассматривать как элементы С и ≤c требуемой лингвистической онтологии. Парсеры языка (например, проект АОТ [6]) могут быть успешно использованы как для определения ролей концептов, так и для определения их атрибутов. То, чего действительно не хватает для полноценной интеллектуальной системы, так это систематизированного репертуара лексико-синтаксических единиц языка, несущих в себе однозначно трактуемую семантику и одновременно выполняющих роль «элементарных единиц сборки» высказываний (текстов). Пересечение такого репертуара «архе-функций», несомых синтаксической формой и репертуара словносителей категориальных референций, дает проекцию однозначно трактуемой роли (функции) выполняемой данным понятием. Подобный систематизирующий труд, как было сказано выше, выполнен в значительной степени Золотовой Г.А. [8] и ждет достойной технической реализации.\nИС для автоматизированного\nобнаружения концептов онтологии ПО\nПредлагаемый подход автоматизированного построения онтологии ПО, сочетает в себе быстроту статистических методов и точность\nлингвистического подхода с позиций синтаксем (или лингвистических шаблонов).\nПроцесс построения онтолгии состоит из\nнескольких последовательных этапов:\n1. Разметка корпуса синтаксическими тегами (напрмер, информацией о части речи, роде\nчисле и т.д.).\n2. Определение характерных, т.е. наиболее часто встречающихся в корпусе\nлингвистических структур и формирование на их основе лигвистических шаблонов. 3. Поиск фрагментов текста, соответвующих данным шаблонам. 4. Нормализация и добавление в базовую онтологию новых концептов, выявленных\nна предыдущем этапе.\nНа третьем этапе необходимо привлечение эксперта предметной области для оценки релевантности найденных потенциальных концептов.\nПроиллюстируем сказанное примером\nанализа следующего текста (фрагмент рекомендации МАГАТЭ 2000 г.):\n«После аварийного облучения большой\nмощности развитие поражений по времени проходит через четко определенные стадии. Продолжительность и время наступления стадий зависит от дозы. Малые дозы не дают наблюдаемых эффектов. Типичное развитие событий после облучения всего тела от источника проникающей радиации включает начальную продромальную стадию с такими симптомами, как тошнота, рвота, усталость и, возможно, лихорадка и диарея, после чего следует латентный период различной продолжительности.»\nМодуль лингвистической онтологии ИС\nраспознает такие свойства концептов: квалитатив\n(качество) субъекта и его объект. В русском языке это может выражаться следующими формулами:\n1. вспомогательными глаголами {отличаться, выражаться, проявляться, характеризоваться,\nобладать} + Т.п. признакового слова (предицирующий компонент); 2. c помощью родительного падежа, когда предицирущий компонент определен\nсочетанием {прилагательное + существительное}; 3. в эксплицитной форме конструкцией типа «объект может иметь такие {характеристики,\nсвойства, признаки}».\n4. с помощью связанной синтаксемы с родительным падежом, обозначающей объект при отглагольном существительном.\nОбнаружение синтаксических характеристик выполняется прасером русского языка (АОТ-парсер [10]), способным распознавать грамматические формы встречаемых слов. Для правильной работы определяется также порядок применения (приоритет) правил.\nОпределяются свойства концепта\n«облучение», т.е. система применяет описанные правила только к тем предложениям, в которых обнаружит любую словоформу «облучение».\nТаким образом, имеем возможность\nобнаружить в тексте и истолковать, например, следующие свойства термина:\n«…облучения большой мощности»  правило\n2; «мощность» – атрибут концепта «облучение»;\n«…облучение всего тела»  правило 4;\nпредикат «облучать» и его объект «тело»;\nПреимуществом предлагаемого метода\nявляется то, что «точками входа» для анализа текста могут служить и слова и собственно синтаксемы.\nСтруктура ИС представлена на рис.1:\nРис.1. Фреймворк ИС на основе синтаксем\nИС состоит из следующих модулей: Модуль базовой онтологии (БО) построен\nвручную с помощью эксперта ПО.В настоящий момент базовая онтология, представленная на OWL содержит около 30 концептов и описывающих их отношений. БО одновременно служит «фильтром» для отбора фрагментов текста, потенциально содержащих информацию, которая позволит либо добавить новые свойства для существующих концептов БО, либо добавить новые концепты в БО (с их свойствами) и получить расширенную онтологию (РО).\nМодуль лингвистической разметки, основой\nкоторого служит парсер языка. На выходе этого модуля получаем фрагменты текста, снабженные необходимой синтаксической информацией для дальнейшей обработки.\nМодуль синтаксем русского языка (основной\nмодуль ИС), включающий в себя словарь типа WordNet (аналоги для русского языка RuNet, RussNet), объединяющий слова в группы синонимов.\nМодуль нормализации свойств,\nпреобразующий найденные на предыдущем этапе данные в формальное представление на OWL и обеспечивающий расширение БО.\nЗаключение\nАнализ текстовой информации и извлечение из\nполнотекстовых документов релевантных данных остается актуальной задачей онтологического инжиниринга в частности. Качественное расширение возможностей ИС возможно при условии внедрения в них модулей, способных извлекать характеристики концептов на основе лингвистического анализа. Одним из возможных способов решения этой задачи является использование лингвистических шаблонов. В данной работе предложен подход к автоматизированному построению (расширению) базовой онтологии на основе синтаксем русского языка. Поскольку каждая синтаксема описывается конечным детерминированным множеством признаков, такой подход является не только возможным, но и предпочтительным, поскольку он обеспечивает однозначное определение свойств концептов создаваемой онтологии. Трудоемкость задачи окупается качеством получаемых результатов. В будущем планируется проверка эффективности метода на большом корпусе, а также возможность его применения для анализа текстов на других языках (аглийский, французский).\nЛитература\n[1] Charlet, J., at al. Apport des outils de TAL a la\nconstruction d’ontologies : propositions au sein de la plateforme DaFOE/ Charlet, J., at al dans TALN 2009, Senlis, 24–26 juin 2009. [2] AI3’s Inaugural State of Tooling for Semantic\nTechnologies/ Adaptive Information Adaptive\nInnovation Adaptive Infrastructure //URL\nhttp://www.mkbergman.com/991/the-state-oftooling-for-semantic-technologies.\n[3] Simperl E., Mochol M. Achieving Maturity: the\nState of Practice in Ontology Engineering in 2009. // In International Journal of Computer Science and Applications, Technomathematics Research Foundation. 2010. Vol. 7 No. 1, P. 45– 65.\n[4] De Nicola, A., & all. A software engineering\napproach to ontology building. // In Information\nSystems 34. 2009. P. 258–275. [5] Makki J., Alquier A.-M., Prince V. Semi\nAutomatic Ontology Instantiation in the domain of Risk Management. // In IFIP, Advances in Information and Communication Technology. 2008. Volume 288. P. 254-265.\n[6] Buitelaar P., Cimiano P., and Magnini B.\nOntology Learning from Texts : An Overview./In Ontology Learning from Text: Methods, Evaluation and Applications. / P. Buitelaar, P. Cimmiano, and B. Magnini, Eds. IOS Press. 2008.\n[7] Zhou, L. Ontology Learning: State of the Art\nand Open Issues. // Information Technology and Management. 2007. 8(3), P.241-252.\n[8] Hearst, M.A., Automatic Acquisition of\nHyponyms from Large Text Corpora. //In: Proceedings of the 14th International Conference on Computational Linguistics. 1992. P 539-545.\n[9] Золотова Г.А. Синтаксический словарь:\nРепертуар элементарых единиц русского синтаксиса. Едиториал УРСС, 2011.\n[10] Проект АОТ// URL:\nhttp://aot.ru/demo/morph.html\nAutomatic Method Of Domain Ontology\nConstruction based on Characteristics of\nCorpora POS-Analysis\nO. Oroinska\nIt is now widely recognized that ontologies,\nare one of the fundamental cornerstones of knowledge-based systems. What is lacking, however, is a currently accepted strategy of how to build ontology; what kinds of the resources and techniques are indispensables to optimize the expenses and the time on the one hand and the amplitude, the completeness, the robustness of en ontology on the other hand. The paper offers a semi-automatic ontology construction method from text corpora in the domain of radiological protection. This method is composed from next steps: 1) text annotation with part-of-speech tags; 2) revelation of the significant linguistic structures and forming the templates; 3) search of text fragments corresponding to these templates; 4) basic ontology instantiation process."
    } ],
    "references" : [ {
      "title" : "Apport des outils de TAL a la construction d’ontologies : propositions au sein de la plateforme DaFOE/ Charlet, J., at al dans TALN 2009, Senlis",
      "author" : [ "J. Charlet", "at al" ],
      "venue" : "juin",
      "citeRegEx" : "1",
      "shortCiteRegEx" : "1",
      "year" : 2009
    }, {
      "title" : "Achieving Maturity: the State of Practice in Ontology Engineering",
      "author" : [ "E. Simperl", "M. Mochol" ],
      "venue" : "In International Journal of Computer Science and Applications, Technomathematics Research Foundation",
      "citeRegEx" : "3",
      "shortCiteRegEx" : "3",
      "year" : 2009
    }, {
      "title" : "A software engineering approach to ontology building",
      "author" : [ "A. De Nicola" ],
      "venue" : "Information Systems",
      "citeRegEx" : "4",
      "shortCiteRegEx" : "4",
      "year" : 2009
    }, {
      "title" : "Semi Automatic Ontology Instantiation in the domain of Risk Management",
      "author" : [ "J. Makki", "A.-M. Alquier", "V. Prince" ],
      "venue" : "IFIP, Advances in Information and Communication Technology",
      "citeRegEx" : "5",
      "shortCiteRegEx" : "5",
      "year" : 2008
    }, {
      "title" : "Ontology Learning from Texts : An Overview./In Ontology Learning from Text: Methods, Evaluation and Applications",
      "author" : [ "P. Buitelaar", "P. Cimiano", "B. Magnini" ],
      "venue" : null,
      "citeRegEx" : "6",
      "shortCiteRegEx" : "6",
      "year" : 2008
    }, {
      "title" : "Ontology Learning: State of the Art and Open Issues",
      "author" : [ "L. Zhou" ],
      "venue" : "Information Technology and Management",
      "citeRegEx" : "7",
      "shortCiteRegEx" : "7",
      "year" : 2007
    }, {
      "title" : "Automatic Acquisition of Hyponyms from Large Text Corpora",
      "author" : [ "M.A. Hearst" ],
      "venue" : "//In: Proceedings of the 14th International Conference on Computational Linguistics",
      "citeRegEx" : "8",
      "shortCiteRegEx" : "8",
      "year" : 1992
    } ],
    "referenceMentions" : [ {
      "referenceID" : 1,
      "context" : "Со ссылкой на [2],[3] можно утверждать, что в 2011 г.",
      "startOffset" : 18,
      "endOffset" : 21
    }, {
      "referenceID" : 2,
      "context" : "Обобщая множество сходных определений, напомним, что в настоящее время под онтологией подразумаевается семантическая структура, в явном виде описывающая основные понятия (концепты) предметной области (ПО), связывающие их отношения, а также аксиомы, описывающие правила вывода новых концептов [4].",
      "startOffset" : 292,
      "endOffset" : 295
    }, {
      "referenceID" : 3,
      "context" : "С появлением сетевых лексических ресурсов и совершенствованием синтаксических анализаторов линвистические методы привлекают все большее внимание специалистов благодаря высокому качеству результатов, которые обещают такие методы [5].",
      "startOffset" : 228,
      "endOffset" : 231
    }, {
      "referenceID" : 4,
      "context" : "[6],",
      "startOffset" : 0,
      "endOffset" : 3
    }, {
      "referenceID" : 5,
      "context" : "сравнению с результатами работы экспертов [7]).",
      "startOffset" : 42,
      "endOffset" : 45
    }, {
      "referenceID" : 6,
      "context" : "Hearst [8].",
      "startOffset" : 7,
      "endOffset" : 10
    }, {
      "referenceID" : 4,
      "context" : "Математически онтология определяется следующим образом [6]:",
      "startOffset" : 55,
      "endOffset" : 58
    }, {
      "referenceID" : 4,
      "context" : "Парсеры языка (например, проект АОТ [6]) могут быть успешно использованы как для определения ролей концептов, так и для определения их атрибутов.",
      "startOffset" : 36,
      "endOffset" : 39
    }, {
      "referenceID" : 6,
      "context" : "[8] и ждет достойной технической реализации.",
      "startOffset" : 0,
      "endOffset" : 3
    }, {
      "referenceID" : 0,
      "context" : "[1] Charlet, J.",
      "startOffset" : 0,
      "endOffset" : 3
    }, {
      "referenceID" : 1,
      "context" : "[3] Simperl E.",
      "startOffset" : 0,
      "endOffset" : 3
    }, {
      "referenceID" : 2,
      "context" : "[4] De Nicola, A.",
      "startOffset" : 0,
      "endOffset" : 3
    }, {
      "referenceID" : 3,
      "context" : "[5] Makki J.",
      "startOffset" : 0,
      "endOffset" : 3
    }, {
      "referenceID" : 4,
      "context" : "[6] Buitelaar P.",
      "startOffset" : 0,
      "endOffset" : 3
    }, {
      "referenceID" : 5,
      "context" : "[7] Zhou, L.",
      "startOffset" : 0,
      "endOffset" : 3
    }, {
      "referenceID" : 6,
      "context" : "[8] Hearst, M.",
      "startOffset" : 0,
      "endOffset" : 3
    } ],
    "year" : 2014,
    "abstractText" : "Вызов сегодняшнего дня, обусловленный бурным ростом текстовых хранилищ в глобальной сети Интернет, заключается в том, чтобы «научить» сами информационные системы (ИС) обнаруживать и правильно интерпретировать полезную информацию, предоставляемую текстом. Разработка методов автоматического анализа текстовой информации и извлечение из полнотекстовых документов релевантных данных является актуальной задачей инженерии знаний в целом и онтологического инжиниринга в частности. Предпосылкой появления прорывных технологий, которые позволи бы ее решить автор считает поиск решений на основе методов системного анализа, как самого объекта исследования  текста, так и поставленных прикладных задач, которые должны быть решены в результате такой обработки. Иными словами, для семантического анализа текстовой информации требуется онтологический подход, т.е. чтобы обнаружить в тексте требуемую информацию, сама ИС должна обладать достаточным объемом лингвистических знаний.",
    "creator" : "Microsoft® Office Word 2007"
  }
}